parse_sse/__init__.py
parse_sse/parse.py
parse_sse-0.0.0.1.dist-info/LICENSE
parse_sse-0.0.0.1.dist-info/METADATA
parse_sse-0.0.0.1.dist-info/WHEEL
parse_sse-0.0.0.1.dist-info/top_level.txt
parse_sse-0.0.0.1.dist-info/RECORD
