Metadata-Version: 2.1
Name: parse-sse
Version: 0.0.0.1
Summary: Logic for parse SSE event
Author: Gavin Bao
Author-email: xingce.bao@gmail.com
License: MIT
License-File: LICENSE
Requires-Dist: requests
